backuppc_clone
