Metadata-Version: 1.1
Name: BackupPC-Clone
Version: 1.0.1
Summary: A tool for cloning the data of a BackupPC instance
Home-page: https://github.com/SetBased/BackupPC-Clone
Author: Set Based IT Consultancy
Author-email: info@setbased.nl
License: MIT
Keywords: BackupPC,clone,copy
Platform: UNKNOWN
Classifier: Development Status :: 5 - Production/Stable
Classifier: Intended Audience :: System Administrators
Classifier: Topic :: System :: Archiving :: Backup
Classifier: License :: OSI Approved :: MIT License
Classifier: Programming Language :: Python :: 3
Classifier: Programming Language :: Python :: 3.5
Classifier: Programming Language :: Python :: 3.6
Classifier: Programming Language :: Python :: 3.7
